{
  "chapter": {
    "id": "section-data-section-1747509428534-730",
    "chapterNumber": -2,
    "title": "Section: undefined",
    "content": "# Section: undefined\n\n## Overview\n- Chapters: 33-40\n- Theme: 社会的意義と持続可能な成長\n- Learning Concept: パーパスドリブン経営\n\n## Narrative Progression\nPhase: 統合と超越\nMotifs: 森, 川, 循環, 布\n\n## Character Evolution\nMain Characters: 田中誠, 鈴木美咲, 山田雄一, 佐藤エミ\n\n## Learning Journey\nPrimary Stage: INTEGRATION\nObjectives: 経済的価値と社会的価値の両立可能性を理解する, 自己と社会の繋がりを実感し、より大きな目的に奉仕する喜びを体感する, ビジネスに社会的意義を統合し、持続可能な成長モデルを構築できるようになる\n\n## Technical Data\n{\n  \"sectionInfo\": {\n    \"id\": \"section-1747509428534-730\",\n    \"chapterRange\": {\n      \"start\": 33,\n      \"end\": 40\n    },\n    \"structure\": {\n      \"id\": \"section-1747509428534-730\",\n      \"number\": 5,\n      \"chapterRange\": {\n        \"start\": 33,\n        \"end\": 40\n      },\n      \"narrativePhase\": \"統合と超越\",\n      \"theme\": \"社会的意義と持続可能な成長\",\n      \"motifs\": [\n        \"森\",\n        \"川\",\n        \"循環\",\n        \"布\"\n      ],\n      \"setting\": \"拡大するビジネスエコシステムと社会との接点\"\n    },\n    \"learningJourneyDesign\": {\n      \"mainConcept\": \"パーパスドリブン経営\",\n      \"secondaryConcepts\": [\n        \"共有価値の創造(CSV)\",\n        \"ステークホルダー資本主義\",\n        \"再生型ビジネス\"\n      ],\n      \"primaryLearningStage\": \"INTEGRATION\",\n      \"secondaryLearningStages\": [\n        \"APPLICATION\"\n      ],\n      \"learningObjectives\": {\n        \"cognitive\": \"経済的価値と社会的価値の両立可能性を理解する\",\n        \"affective\": \"自己と社会の繋がりを実感し、より大きな目的に奉仕する喜びを体感する\",\n        \"behavioral\": \"ビジネスに社会的意義を統合し、持続可能な成長モデルを構築できるようになる\"\n      },\n      \"transformationalArc\": {\n        \"startingState\": \"事業の成長と収益性追求が中心、社会的視点は付加的\",\n        \"challenges\": [\n          \"短期的利益と長期的意義の葛藤\",\n          \"異なる価値観の統合\",\n          \"持続可能性の障壁\"\n        ],\n        \"insights\": [\n          \"社会的意義と経済的価値が相互補強する可能性\",\n          \"目的と利益の両立\"\n        ],\n        \"endState\": \"パーパスを中心に据えた持続可能なビジネスモデルの確立\"\n      },\n      \"conceptEmbodiments\": {\n        \"metaphors\": [\n          \"森の生態系\",\n          \"川の流れと循環\",\n          \"様々な糸が織りなす布\"\n        ],\n        \"situations\": [\n          \"短期的利益と長期的意義の間で葛藤する場面\",\n          \"社会的課題と事業の接点を発見する場面\",\n          \"多様なステークホルダーと共に価値を創造する場面\"\n        ],\n        \"dialogueThemes\": [\n          \"目的と利益\",\n          \"社会と事業の統合\",\n          \"持続可能性\"\n        ]\n      }\n    },\n    \"emotionalDesign\": {\n      \"emotionalArc\": {\n        \"opening\": \"迷いと省察\",\n        \"midpoint\": \"覚悟と決断\",\n        \"conclusion\": \"調和と充足\"\n      },\n      \"tensionPoints\": [\n        {\n          \"relativePosition\": 0.15,\n          \"intensity\": 0.7,\n          \"description\": \"成長の過程で生じた価値観の揺らぎ\"\n        },\n        {\n          \"relativePosition\": 0.45,\n          \"intensity\": 0.75,\n          \"description\": \"パーパス追求と経済的現実のジレンマ\"\n        },\n        {\n          \"relativePosition\": 0.75,\n          \"intensity\": 0.85,\n          \"description\": \"重要なパートナーとの価値観の衝突\"\n        }\n      ],\n      \"catharticMoment\": {\n        \"relativePosition\": 0.85,\n        \"type\": \"transformative\",\n        \"description\": \"事業を通じて実際に社会変化を起こした成果を目の当たりにする\"\n      },\n      \"readerEmotionalJourney\": \"主人公の成功の先にある空虚感と新たな問いに共感し、より大きな意義を求める模索に寄り添う。葛藤と覚悟の過程を経て、自己と社会の調和、経済価値と社会価値の統合という深い満足感を共有する\",\n      \"emotionalPayoff\": \"自己実現と社会貢献の統合による深い充足感と目的の達成\"\n    },\n    \"characterDesign\": {\n      \"mainCharacters\": [\n        \"田中誠\",\n        \"鈴木美咲\",\n        \"山田雄一\",\n        \"佐藤エミ\"\n      ],\n      \"characterRoles\": {\n        \"田中誠\": {\n          \"learningRole\": \"reflector\",\n          \"narrativeFunction\": \"パーパスと経済の統合を目指す\"\n        },\n        \"鈴木美咲\": {\n          \"learningRole\": \"supporter\",\n          \"narrativeFunction\": \"理想と現実のバランスを促す\"\n        },\n        \"山田雄一\": {\n          \"learningRole\": \"mentor\",\n          \"narrativeFunction\": \"社会的インパクトの視点を提供\"\n        },\n        \"佐藤エミ\": {\n          \"learningRole\": \"reflector\",\n          \"narrativeFunction\": \"事業の社会的意味を問いかける\"\n        }\n      },\n      \"relationshipDevelopments\": [\n        {\n          \"characters\": [\n            \"田中誠\",\n            \"鈴木美咲\"\n          ],\n          \"startingDynamic\": \"深いパートナーシップ\",\n          \"evolution\": \"新たな役割の探求→価値観の再共有\",\n          \"endDynamic\": \"使命を共にする共同創業者\"\n        },\n        {\n          \"characters\": [\n            \"田中誠\",\n            \"佐藤エミ\"\n          ],\n          \"startingDynamic\": \"緊張\",\n          \"evolution\": \"傾聴→共創→信頼\",\n          \"endDynamic\": \"相互貢献\"\n        }\n      ],\n      \"characterTransformations\": {\n        \"田中誠\": {\n          \"startingState\": \"成功志向\",\n          \"internalObstacles\": [\n            \"成功の定義への執着\",\n            \"短期的思考\",\n            \"社会と自己の分離感\"\n          ],\n          \"growthMoments\": [\n            \"事業の成功の先にある空虚感に直面\",\n            \"社会的課題と事業の深い接点を発見\",\n            \"経済的価値と社会的価値の統合モデルを確立\"\n          ],\n          \"endState\": \"パーパスと調和した豊かな成功観\"\n        }\n      }\n    },\n    \"narrativeStructureDesign\": {\n      \"keyScenes\": [\n        {\n          \"description\": \"事業の成功達成後に感じる「これだけではない」という感覚\",\n          \"purpose\": \"新たな問いの提起\",\n          \"relativePosition\": 0.1,\n          \"learningConnection\": \"表面的成功の先にある意義の探求\"\n        },\n        {\n          \"description\": \"自社の事業が社会に与える影響の発見\",\n          \"purpose\": \"視野の拡大\",\n          \"relativePosition\": 0.3,\n          \"learningConnection\": \"事業と社会の接点認識\"\n        },\n        {\n          \"description\": \"事業と社会貢献を統合する本質的目的の言語化\",\n          \"purpose\": \"パーパスの明確化\",\n          \"relativePosition\": 0.5,\n          \"learningConnection\": \"経済価値と社会価値の接点発見\"\n        },\n        {\n          \"description\": \"経済的成功と社会的意義が相互強化する瞬間\",\n          \"purpose\": \"統合の実証\",\n          \"relativePosition\": 0.9,\n          \"learningConnection\": \"パーパスドリブン経営の実現\"\n        }\n      ],\n      \"turningPoints\": [\n        {\n          \"description\": \"「収益の先にある本当の目的」への気づき\",\n          \"impact\": \"経営の根本的方向転換\",\n          \"relativePosition\": 0.45\n        },\n        {\n          \"description\": \"「社会貢献と事業成長は対立ではなく相乗効果を持つ」という確信\",\n          \"impact\": \"ビジネスと社会貢献の統合モデル確立\",\n          \"relativePosition\": 0.8\n        }\n      ],\n      \"narrativeThreads\": [\n        {\n          \"thread\": \"パーパスの探求\",\n          \"development\": \"表面的成功から本質的意義への移行\"\n        },\n        {\n          \"thread\": \"持続可能性の追求\",\n          \"development\": \"短期的な利益から長期的価値創造への転換\"\n        },\n        {\n          \"thread\": \"関係性の拡大\",\n          \"development\": \"顧客やチームから社会全体へと視野を広げる過程\"\n        }\n      ],\n      \"sectionForeshadowing\": [\n        {\n          \"element\": \"主人公の原体験\",\n          \"plantingPoint\": 33,\n          \"payoffSection\": 5\n        },\n        {\n          \"element\": \"社会起業家の挑戦\",\n          \"plantingPoint\": 35,\n          \"payoffSection\": 5\n        }\n      ],\n      \"intersectionWithOtherSections\": {\n        \"previous\": \"組織内の心理的安全性と集合知を基盤に、より広い社会的文脈へと視野を広げる\",\n        \"next\": \"物語の完結。初期の「なぜ」がより深く豊かな形で実現される循環構造\"\n      }\n    },\n    \"metaInformation\": {\n      \"created\": \"2025-05-17T19:17:08.534Z\",\n      \"lastModified\": \"2025-05-17T19:17:08.547Z\",\n      \"version\": 2,\n      \"editorNotes\": \"中期プロットからインポート: undefined\",\n      \"generationPrompts\": [],\n      \"relationToOverallStory\": \"\"\n    }\n  },\n  \"relatedChapters\": [],\n  \"narrativeProgression\": {\n    \"phase\": \"統合と超越\",\n    \"theme\": \"社会的意義と持続可能な成長\",\n    \"motifs\": [\n      \"森\",\n      \"川\",\n      \"循環\",\n      \"布\"\n    ],\n    \"emotionalArc\": {\n      \"opening\": \"迷いと省察\",\n      \"midpoint\": \"覚悟と決断\",\n      \"conclusion\": \"調和と充足\"\n    },\n    \"keyScenes\": [\n      {\n        \"description\": \"事業の成功達成後に感じる「これだけではない」という感覚\",\n        \"purpose\": \"新たな問いの提起\",\n        \"relativePosition\": 0.1,\n        \"learningConnection\": \"表面的成功の先にある意義の探求\"\n      },\n      {\n        \"description\": \"自社の事業が社会に与える影響の発見\",\n        \"purpose\": \"視野の拡大\",\n        \"relativePosition\": 0.3,\n        \"learningConnection\": \"事業と社会の接点認識\"\n      },\n      {\n        \"description\": \"事業と社会貢献を統合する本質的目的の言語化\",\n        \"purpose\": \"パーパスの明確化\",\n        \"relativePosition\": 0.5,\n        \"learningConnection\": \"経済価値と社会価値の接点発見\"\n      },\n      {\n        \"description\": \"経済的成功と社会的意義が相互強化する瞬間\",\n        \"purpose\": \"統合の実証\",\n        \"relativePosition\": 0.9,\n        \"learningConnection\": \"パーパスドリブン経営の実現\"\n      }\n    ],\n    \"turningPoints\": [\n      {\n        \"description\": \"「収益の先にある本当の目的」への気づき\",\n        \"impact\": \"経営の根本的方向転換\",\n        \"relativePosition\": 0.45\n      },\n      {\n        \"description\": \"「社会貢献と事業成長は対立ではなく相乗効果を持つ」という確信\",\n        \"impact\": \"ビジネスと社会貢献の統合モデル確立\",\n        \"relativePosition\": 0.8\n      }\n    ]\n  },\n  \"characterEvolution\": {\n    \"mainCharacters\": [\n      \"田中誠\",\n      \"鈴木美咲\",\n      \"山田雄一\",\n      \"佐藤エミ\"\n    ],\n    \"characterRoles\": {\n      \"田中誠\": {\n        \"learningRole\": \"reflector\",\n        \"narrativeFunction\": \"パーパスと経済の統合を目指す\"\n      },\n      \"鈴木美咲\": {\n        \"learningRole\": \"supporter\",\n        \"narrativeFunction\": \"理想と現実のバランスを促す\"\n      },\n      \"山田雄一\": {\n        \"learningRole\": \"mentor\",\n        \"narrativeFunction\": \"社会的インパクトの視点を提供\"\n      },\n      \"佐藤エミ\": {\n        \"learningRole\": \"reflector\",\n        \"narrativeFunction\": \"事業の社会的意味を問いかける\"\n      }\n    },\n    \"relationshipDevelopments\": [\n      {\n        \"characters\": [\n          \"田中誠\",\n          \"鈴木美咲\"\n        ],\n        \"startingDynamic\": \"深いパートナーシップ\",\n        \"evolution\": \"新たな役割の探求→価値観の再共有\",\n        \"endDynamic\": \"使命を共にする共同創業者\"\n      },\n      {\n        \"characters\": [\n          \"田中誠\",\n          \"佐藤エミ\"\n        ],\n        \"startingDynamic\": \"緊張\",\n        \"evolution\": \"傾聴→共創→信頼\",\n        \"endDynamic\": \"相互貢献\"\n      }\n    ],\n    \"transformations\": {\n      \"田中誠\": {\n        \"startingState\": \"成功志向\",\n        \"internalObstacles\": [\n          \"成功の定義への執着\",\n          \"短期的思考\",\n          \"社会と自己の分離感\"\n        ],\n        \"growthMoments\": [\n          \"事業の成功の先にある空虚感に直面\",\n          \"社会的課題と事業の深い接点を発見\",\n          \"経済的価値と社会的価値の統合モデルを確立\"\n        ],\n        \"endState\": \"パーパスと調和した豊かな成功観\"\n      }\n    }\n  },\n  \"learningProgression\": {\n    \"mainConcept\": \"パーパスドリブン経営\",\n    \"learningStage\": \"INTEGRATION\",\n    \"objectives\": {\n      \"cognitive\": \"経済的価値と社会的価値の両立可能性を理解する\",\n      \"affective\": \"自己と社会の繋がりを実感し、より大きな目的に奉仕する喜びを体感する\",\n      \"behavioral\": \"ビジネスに社会的意義を統合し、持続可能な成長モデルを構築できるようになる\"\n    },\n    \"transformationalArc\": {\n      \"startingState\": \"事業の成長と収益性追求が中心、社会的視点は付加的\",\n      \"challenges\": [\n        \"短期的利益と長期的意義の葛藤\",\n        \"異なる価値観の統合\",\n        \"持続可能性の障壁\"\n      ],\n      \"insights\": [\n        \"社会的意義と経済的価値が相互補強する可能性\",\n        \"目的と利益の両立\"\n      ],\n      \"endState\": \"パーパスを中心に据えた持続可能なビジネスモデルの確立\"\n    }\n  }\n}",
    "createdAt": "2025-06-01T07:33:20.195Z",
    "updatedAt": "2025-06-01T07:33:20.195Z",
    "scenes": [],
    "metadata": {
      "qualityScore": 0.9,
      "keywords": [
        "section-plot",
        "社会的意義と持続可能な成長",
        "森",
        "川",
        "循環",
        "布"
      ],
      "events": [],
      "characters": [
        "田中誠",
        "鈴木美咲",
        "山田雄一",
        "佐藤エミ"
      ],
      "foreshadowing": [],
      "resolutions": [],
      "correctionHistory": [],
      "pov": "System",
      "location": "拡大するビジネスエコシステムと社会との接点",
      "emotionalTone": "structured"
    }
  },
  "content": "# Section: undefined\n\n## Overview\n- Chapters: 33-40\n- Theme: 社会的意義と持続可能な成長\n- Learning Concept: パーパスドリブン経営\n\n## Narrative Progression\nPhase: 統合と超越\nMotifs: 森, 川, 循環, 布\n\n## Character Evolution\nMain Characters: 田中誠, 鈴木美咲, 山田雄一, 佐藤エミ\n\n## Learning Journey\nPrimary Stage: INTEGRATION\nObjectives: 経済的価値と社会的価値の両立可能性を理解する, 自己と社会の繋がりを実感し、より大きな目的に奉仕する喜びを体感する, ビジネスに社会的意義を統合し、持続可能な成長モデルを構築できるようになる\n\n## Technical Data\n{\n  \"sectionInfo\": {\n    \"id\": \"section-1747509428534-730\",\n    \"chapterRange\": {\n      \"start\": 33,\n      \"end\": 40\n    },\n    \"structure\": {\n      \"id\": \"section-1747509428534-730\",\n      \"number\": 5,\n      \"chapterRange\": {\n        \"start\": 33,\n        \"end\": 40\n      },\n      \"narrativePhase\": \"統合と超越\",\n      \"theme\": \"社会的意義と持続可能な成長\",\n      \"motifs\": [\n        \"森\",\n        \"川\",\n        \"循環\",\n        \"布\"\n      ],\n      \"setting\": \"拡大するビジネスエコシステムと社会との接点\"\n    },\n    \"learningJourneyDesign\": {\n      \"mainConcept\": \"パーパスドリブン経営\",\n      \"secondaryConcepts\": [\n        \"共有価値の創造(CSV)\",\n        \"ステークホルダー資本主義\",\n        \"再生型ビジネス\"\n      ],\n      \"primaryLearningStage\": \"INTEGRATION\",\n      \"secondaryLearningStages\": [\n        \"APPLICATION\"\n      ],\n      \"learningObjectives\": {\n        \"cognitive\": \"経済的価値と社会的価値の両立可能性を理解する\",\n        \"affective\": \"自己と社会の繋がりを実感し、より大きな目的に奉仕する喜びを体感する\",\n        \"behavioral\": \"ビジネスに社会的意義を統合し、持続可能な成長モデルを構築できるようになる\"\n      },\n      \"transformationalArc\": {\n        \"startingState\": \"事業の成長と収益性追求が中心、社会的視点は付加的\",\n        \"challenges\": [\n          \"短期的利益と長期的意義の葛藤\",\n          \"異なる価値観の統合\",\n          \"持続可能性の障壁\"\n        ],\n        \"insights\": [\n          \"社会的意義と経済的価値が相互補強する可能性\",\n          \"目的と利益の両立\"\n        ],\n        \"endState\": \"パーパスを中心に据えた持続可能なビジネスモデルの確立\"\n      },\n      \"conceptEmbodiments\": {\n        \"metaphors\": [\n          \"森の生態系\",\n          \"川の流れと循環\",\n          \"様々な糸が織りなす布\"\n        ],\n        \"situations\": [\n          \"短期的利益と長期的意義の間で葛藤する場面\",\n          \"社会的課題と事業の接点を発見する場面\",\n          \"多様なステークホルダーと共に価値を創造する場面\"\n        ],\n        \"dialogueThemes\": [\n          \"目的と利益\",\n          \"社会と事業の統合\",\n          \"持続可能性\"\n        ]\n      }\n    },\n    \"emotionalDesign\": {\n      \"emotionalArc\": {\n        \"opening\": \"迷いと省察\",\n        \"midpoint\": \"覚悟と決断\",\n        \"conclusion\": \"調和と充足\"\n      },\n      \"tensionPoints\": [\n        {\n          \"relativePosition\": 0.15,\n          \"intensity\": 0.7,\n          \"description\": \"成長の過程で生じた価値観の揺らぎ\"\n        },\n        {\n          \"relativePosition\": 0.45,\n          \"intensity\": 0.75,\n          \"description\": \"パーパス追求と経済的現実のジレンマ\"\n        },\n        {\n          \"relativePosition\": 0.75,\n          \"intensity\": 0.85,\n          \"description\": \"重要なパートナーとの価値観の衝突\"\n        }\n      ],\n      \"catharticMoment\": {\n        \"relativePosition\": 0.85,\n        \"type\": \"transformative\",\n        \"description\": \"事業を通じて実際に社会変化を起こした成果を目の当たりにする\"\n      },\n      \"readerEmotionalJourney\": \"主人公の成功の先にある空虚感と新たな問いに共感し、より大きな意義を求める模索に寄り添う。葛藤と覚悟の過程を経て、自己と社会の調和、経済価値と社会価値の統合という深い満足感を共有する\",\n      \"emotionalPayoff\": \"自己実現と社会貢献の統合による深い充足感と目的の達成\"\n    },\n    \"characterDesign\": {\n      \"mainCharacters\": [\n        \"田中誠\",\n        \"鈴木美咲\",\n        \"山田雄一\",\n        \"佐藤エミ\"\n      ],\n      \"characterRoles\": {\n        \"田中誠\": {\n          \"learningRole\": \"reflector\",\n          \"narrativeFunction\": \"パーパスと経済の統合を目指す\"\n        },\n        \"鈴木美咲\": {\n          \"learningRole\": \"supporter\",\n          \"narrativeFunction\": \"理想と現実のバランスを促す\"\n        },\n        \"山田雄一\": {\n          \"learningRole\": \"mentor\",\n          \"narrativeFunction\": \"社会的インパクトの視点を提供\"\n        },\n        \"佐藤エミ\": {\n          \"learningRole\": \"reflector\",\n          \"narrativeFunction\": \"事業の社会的意味を問いかける\"\n        }\n      },\n      \"relationshipDevelopments\": [\n        {\n          \"characters\": [\n            \"田中誠\",\n            \"鈴木美咲\"\n          ],\n          \"startingDynamic\": \"深いパートナーシップ\",\n          \"evolution\": \"新たな役割の探求→価値観の再共有\",\n          \"endDynamic\": \"使命を共にする共同創業者\"\n        },\n        {\n          \"characters\": [\n            \"田中誠\",\n            \"佐藤エミ\"\n          ],\n          \"startingDynamic\": \"緊張\",\n          \"evolution\": \"傾聴→共創→信頼\",\n          \"endDynamic\": \"相互貢献\"\n        }\n      ],\n      \"characterTransformations\": {\n        \"田中誠\": {\n          \"startingState\": \"成功志向\",\n          \"internalObstacles\": [\n            \"成功の定義への執着\",\n            \"短期的思考\",\n            \"社会と自己の分離感\"\n          ],\n          \"growthMoments\": [\n            \"事業の成功の先にある空虚感に直面\",\n            \"社会的課題と事業の深い接点を発見\",\n            \"経済的価値と社会的価値の統合モデルを確立\"\n          ],\n          \"endState\": \"パーパスと調和した豊かな成功観\"\n        }\n      }\n    },\n    \"narrativeStructureDesign\": {\n      \"keyScenes\": [\n        {\n          \"description\": \"事業の成功達成後に感じる「これだけではない」という感覚\",\n          \"purpose\": \"新たな問いの提起\",\n          \"relativePosition\": 0.1,\n          \"learningConnection\": \"表面的成功の先にある意義の探求\"\n        },\n        {\n          \"description\": \"自社の事業が社会に与える影響の発見\",\n          \"purpose\": \"視野の拡大\",\n          \"relativePosition\": 0.3,\n          \"learningConnection\": \"事業と社会の接点認識\"\n        },\n        {\n          \"description\": \"事業と社会貢献を統合する本質的目的の言語化\",\n          \"purpose\": \"パーパスの明確化\",\n          \"relativePosition\": 0.5,\n          \"learningConnection\": \"経済価値と社会価値の接点発見\"\n        },\n        {\n          \"description\": \"経済的成功と社会的意義が相互強化する瞬間\",\n          \"purpose\": \"統合の実証\",\n          \"relativePosition\": 0.9,\n          \"learningConnection\": \"パーパスドリブン経営の実現\"\n        }\n      ],\n      \"turningPoints\": [\n        {\n          \"description\": \"「収益の先にある本当の目的」への気づき\",\n          \"impact\": \"経営の根本的方向転換\",\n          \"relativePosition\": 0.45\n        },\n        {\n          \"description\": \"「社会貢献と事業成長は対立ではなく相乗効果を持つ」という確信\",\n          \"impact\": \"ビジネスと社会貢献の統合モデル確立\",\n          \"relativePosition\": 0.8\n        }\n      ],\n      \"narrativeThreads\": [\n        {\n          \"thread\": \"パーパスの探求\",\n          \"development\": \"表面的成功から本質的意義への移行\"\n        },\n        {\n          \"thread\": \"持続可能性の追求\",\n          \"development\": \"短期的な利益から長期的価値創造への転換\"\n        },\n        {\n          \"thread\": \"関係性の拡大\",\n          \"development\": \"顧客やチームから社会全体へと視野を広げる過程\"\n        }\n      ],\n      \"sectionForeshadowing\": [\n        {\n          \"element\": \"主人公の原体験\",\n          \"plantingPoint\": 33,\n          \"payoffSection\": 5\n        },\n        {\n          \"element\": \"社会起業家の挑戦\",\n          \"plantingPoint\": 35,\n          \"payoffSection\": 5\n        }\n      ],\n      \"intersectionWithOtherSections\": {\n        \"previous\": \"組織内の心理的安全性と集合知を基盤に、より広い社会的文脈へと視野を広げる\",\n        \"next\": \"物語の完結。初期の「なぜ」がより深く豊かな形で実現される循環構造\"\n      }\n    },\n    \"metaInformation\": {\n      \"created\": \"2025-05-17T19:17:08.534Z\",\n      \"lastModified\": \"2025-05-17T19:17:08.547Z\",\n      \"version\": 2,\n      \"editorNotes\": \"中期プロットからインポート: undefined\",\n      \"generationPrompts\": [],\n      \"relationToOverallStory\": \"\"\n    }\n  },\n  \"relatedChapters\": [],\n  \"narrativeProgression\": {\n    \"phase\": \"統合と超越\",\n    \"theme\": \"社会的意義と持続可能な成長\",\n    \"motifs\": [\n      \"森\",\n      \"川\",\n      \"循環\",\n      \"布\"\n    ],\n    \"emotionalArc\": {\n      \"opening\": \"迷いと省察\",\n      \"midpoint\": \"覚悟と決断\",\n      \"conclusion\": \"調和と充足\"\n    },\n    \"keyScenes\": [\n      {\n        \"description\": \"事業の成功達成後に感じる「これだけではない」という感覚\",\n        \"purpose\": \"新たな問いの提起\",\n        \"relativePosition\": 0.1,\n        \"learningConnection\": \"表面的成功の先にある意義の探求\"\n      },\n      {\n        \"description\": \"自社の事業が社会に与える影響の発見\",\n        \"purpose\": \"視野の拡大\",\n        \"relativePosition\": 0.3,\n        \"learningConnection\": \"事業と社会の接点認識\"\n      },\n      {\n        \"description\": \"事業と社会貢献を統合する本質的目的の言語化\",\n        \"purpose\": \"パーパスの明確化\",\n        \"relativePosition\": 0.5,\n        \"learningConnection\": \"経済価値と社会価値の接点発見\"\n      },\n      {\n        \"description\": \"経済的成功と社会的意義が相互強化する瞬間\",\n        \"purpose\": \"統合の実証\",\n        \"relativePosition\": 0.9,\n        \"learningConnection\": \"パーパスドリブン経営の実現\"\n      }\n    ],\n    \"turningPoints\": [\n      {\n        \"description\": \"「収益の先にある本当の目的」への気づき\",\n        \"impact\": \"経営の根本的方向転換\",\n        \"relativePosition\": 0.45\n      },\n      {\n        \"description\": \"「社会貢献と事業成長は対立ではなく相乗効果を持つ」という確信\",\n        \"impact\": \"ビジネスと社会貢献の統合モデル確立\",\n        \"relativePosition\": 0.8\n      }\n    ]\n  },\n  \"characterEvolution\": {\n    \"mainCharacters\": [\n      \"田中誠\",\n      \"鈴木美咲\",\n      \"山田雄一\",\n      \"佐藤エミ\"\n    ],\n    \"characterRoles\": {\n      \"田中誠\": {\n        \"learningRole\": \"reflector\",\n        \"narrativeFunction\": \"パーパスと経済の統合を目指す\"\n      },\n      \"鈴木美咲\": {\n        \"learningRole\": \"supporter\",\n        \"narrativeFunction\": \"理想と現実のバランスを促す\"\n      },\n      \"山田雄一\": {\n        \"learningRole\": \"mentor\",\n        \"narrativeFunction\": \"社会的インパクトの視点を提供\"\n      },\n      \"佐藤エミ\": {\n        \"learningRole\": \"reflector\",\n        \"narrativeFunction\": \"事業の社会的意味を問いかける\"\n      }\n    },\n    \"relationshipDevelopments\": [\n      {\n        \"characters\": [\n          \"田中誠\",\n          \"鈴木美咲\"\n        ],\n        \"startingDynamic\": \"深いパートナーシップ\",\n        \"evolution\": \"新たな役割の探求→価値観の再共有\",\n        \"endDynamic\": \"使命を共にする共同創業者\"\n      },\n      {\n        \"characters\": [\n          \"田中誠\",\n          \"佐藤エミ\"\n        ],\n        \"startingDynamic\": \"緊張\",\n        \"evolution\": \"傾聴→共創→信頼\",\n        \"endDynamic\": \"相互貢献\"\n      }\n    ],\n    \"transformations\": {\n      \"田中誠\": {\n        \"startingState\": \"成功志向\",\n        \"internalObstacles\": [\n          \"成功の定義への執着\",\n          \"短期的思考\",\n          \"社会と自己の分離感\"\n        ],\n        \"growthMoments\": [\n          \"事業の成功の先にある空虚感に直面\",\n          \"社会的課題と事業の深い接点を発見\",\n          \"経済的価値と社会的価値の統合モデルを確立\"\n        ],\n        \"endState\": \"パーパスと調和した豊かな成功観\"\n      }\n    }\n  },\n  \"learningProgression\": {\n    \"mainConcept\": \"パーパスドリブン経営\",\n    \"learningStage\": \"INTEGRATION\",\n    \"objectives\": {\n      \"cognitive\": \"経済的価値と社会的価値の両立可能性を理解する\",\n      \"affective\": \"自己と社会の繋がりを実感し、より大きな目的に奉仕する喜びを体感する\",\n      \"behavioral\": \"ビジネスに社会的意義を統合し、持続可能な成長モデルを構築できるようになる\"\n    },\n    \"transformationalArc\": {\n      \"startingState\": \"事業の成長と収益性追求が中心、社会的視点は付加的\",\n      \"challenges\": [\n        \"短期的利益と長期的意義の葛藤\",\n        \"異なる価値観の統合\",\n        \"持続可能性の障壁\"\n      ],\n      \"insights\": [\n        \"社会的意義と経済的価値が相互補強する可能性\",\n        \"目的と利益の両立\"\n      ],\n      \"endState\": \"パーパスを中心に据えた持続可能なビジネスモデルの確立\"\n    }\n  }\n}",
  "metadata": {
    "chapterNumber": -2,
    "wordCount": 9908,
    "characterCount": 0,
    "keyPhraseCount": 6,
    "lastAnalyzed": "2025-06-01T07:33:20.365Z",
    "analysisVersion": "1.0.0"
  },
  "processingState": {
    "analysisCompleted": true,
    "contextGenerated": false,
    "characterStatesExtracted": true,
    "keyPhrasesExtracted": true,
    "lastProcessingTime": "2025-06-01T07:33:20.365Z",
    "processingErrors": []
  },
  "characterState": [],
  "keyPhrases": [
    "「これだけではない」",
    "「収益の先にある本当の目的」",
    "「社会貢献と事業成長は対立ではなく相乗効果を持つ」",
    "「なぜ」",
    "事業を通じて実際に社会変化を起こした",
    "パスと調和した"
  ],
  "timestamp": "2025-06-01T07:33:20.365Z",
  "contentHash": "5ea8bc1b"
}